siteup/__init__.py
siteup/__main__.py
siteup/cli.py
siteup/core.py
siteup-0.1.0.dist-info/WHEEL
siteup-0.1.0.dist-info/METADATA
siteup-0.1.0.dist-info/RECORD
